successor/__init__.py
successor/conventions.py
successor/extension/__init__.py
successor/extension/reflection.py
successor/interpolation/__init__.py
successor/interpolation/linear.py
successor/skaters/__init__.py
successor/skaters/allsuccessorskaters.py
successor/skaters/scalarskaters/__init__.py
successor/skaters/scalarskaters/allscalarskaters.py
successor/skaters/scalarskaters/local.py
successor/skaters/scalarskaters/remote.py
successor/skaters/scalarskaters/scalarskaterfactory.py
successor/skaters/scalarskaters/scalartsaskaters.py
successor/skaters/scalarskaters/sklearnedinventory.py
successor-0.2.0.dist-info/LICENSE
successor-0.2.0.dist-info/METADATA
successor-0.2.0.dist-info/WHEEL
successor-0.2.0.dist-info/entry_points.txt
successor-0.2.0.dist-info/top_level.txt
successor-0.2.0.dist-info/RECORD
